setup.py
repo_monitor/__init__.py
repo_monitor/parser.py
repo_monitor.egg-info/PKG-INFO
repo_monitor.egg-info/SOURCES.txt
repo_monitor.egg-info/dependency_links.txt
repo_monitor.egg-info/entry_points.txt
repo_monitor.egg-info/top_level.txt
repo_monitor/python/__init__.py
repo_monitor/python/deserializers.py
repo_monitor/python/parsers.py