Metadata-Version: 1.0
Name: repo-monitor
Version: 0.1.0
Summary: Utility for monitoring certain aspects of a repo
Home-page: https://github.com/michael-christen/repo-monitor
Author: Michael Christen
Author-email: UNKNOWN
License: MIT
Platform: UNKNOWN
